nepox
